[{"pokemon":"http://www.wikidata.org/entity/Q12478616","pokemonLabel":"Chespin","pokedexNumber":"650","evolFamilyStmt":"http://www.wikidata.org/entity/Q6594304","evolFamilyStmtLabel":"evolutionary line of Chespin","eggGroupStmt":"http://www.wikidata.org/entity/Q26040408","eggGroupStmtLabel":"Field egg group","type":"http://www.wikidata.org/entity/Q25930653","typeLabel":"grass-type Pokémon","colorLabel":"green","heightLabel":"40","weightLabel":"9"},{"pokemon":"http://www.wikidata.org/entity/Q16593800","pokemonLabel":"Quilladin","pokedexNumber":"651","evolFamilyStmt":"http://www.wikidata.org/entity/Q6594304","evolFamilyStmtLabel":"evolutionary line of Chespin","eggGroupStmt":"http://www.wikidata.org/entity/Q26040408","eggGroupStmtLabel":"Field egg group","type":"http://www.wikidata.org/entity/Q25930653","typeLabel":"grass-type Pokémon","colorLabel":"green","heightLabel":"70","weightLabel":"29"},{"pokemon":"http://www.wikidata.org/entity/Q16539557","pokemonLabel":"Chesnaught","pokedexNumber":"652","evolFamilyStmt":"http://www.wikidata.org/entity/Q6594304","evolFamilyStmtLabel":"evolutionary line of Chespin","eggGroupStmt":"http://www.wikidata.org/entity/Q26040408","eggGroupStmtLabel":"Field egg group","type":"http://www.wikidata.org/entity/Q25930532","typeLabel":"fighting-type Pokémon","colorLabel":"green","heightLabel":"160","weightLabel":"90"},{"pokemon":"http://www.wikidata.org/entity/Q16539557","pokemonLabel":"Chesnaught","pokedexNumber":"652","evolFamilyStmt":"http://www.wikidata.org/entity/Q6594304","evolFamilyStmtLabel":"evolutionary line of Chespin","eggGroupStmt":"http://www.wikidata.org/entity/Q26040408","eggGroupStmtLabel":"Field egg group","type":"http://www.wikidata.org/entity/Q25930653","typeLabel":"grass-type Pokémon","colorLabel":"green","heightLabel":"160","weightLabel":"90"},{"pokemon":"http://www.wikidata.org/entity/Q12482861","pokemonLabel":"Fennekin","pokedexNumber":"653","evolFamilyStmt":"http://www.wikidata.org/entity/Q17628300","evolFamilyStmtLabel":"evolutionary line of Fennekin","eggGroupStmt":"http://www.wikidata.org/entity/Q26040408","eggGroupStmtLabel":"Field egg group","type":"http://www.wikidata.org/entity/Q25930490","typeLabel":"Q25930490","colorLabel":"red","heightLabel":"40"},{"pokemon":"http://www.wikidata.org/entity/Q16166749","pokemonLabel":"Braixen","pokedexNumber":"654","evolFamilyStmt":"http://www.wikidata.org/entity/Q17628300","evolFamilyStmtLabel":"evolutionary line of Fennekin","eggGroupStmt":"http://www.wikidata.org/entity/Q26040408","eggGroupStmtLabel":"Field egg group","type":"http://www.wikidata.org/entity/Q25930490","typeLabel":"Q25930490","colorLabel":"red","heightLabel":"100"},{"pokemon":"http://www.wikidata.org/entity/Q16170122","pokemonLabel":"Delphox","pokedexNumber":"655","evolFamilyStmt":"http://www.wikidata.org/entity/Q17628300","evolFamilyStmtLabel":"evolutionary line of Fennekin","eggGroupStmt":"http://www.wikidata.org/entity/Q26040408","eggGroupStmtLabel":"Field egg group","type":"http://www.wikidata.org/entity/Q25930490","typeLabel":"Q25930490","colorLabel":"red","heightLabel":"150","weightLabel":"39"},{"pokemon":"http://www.wikidata.org/entity/Q16170122","pokemonLabel":"Delphox","pokedexNumber":"655","evolFamilyStmt":"http://www.wikidata.org/entity/Q17628300","evolFamilyStmtLabel":"evolutionary line of Fennekin","eggGroupStmt":"http://www.wikidata.org/entity/Q26040408","eggGroupStmtLabel":"Field egg group","type":"http://www.wikidata.org/entity/Q25930740","typeLabel":"psychic-type Pokémon","colorLabel":"red","heightLabel":"150","weightLabel":"39"},{"pokemon":"http://www.wikidata.org/entity/Q12483127","pokemonLabel":"Froakie","pokedexNumber":"656","evolFamilyStmt":"http://www.wikidata.org/entity/Q3716058","evolFamilyStmtLabel":"evolutionary line of Froakie","eggGroupStmt":"http://www.wikidata.org/entity/Q26040640","eggGroupStmtLabel":"Water 1 egg group","type":"http://www.wikidata.org/entity/Q25930495","typeLabel":"water-type Pokémon","colorLabel":"blue","heightLabel":"30","weightLabel":"7"},{"pokemon":"http://www.wikidata.org/entity/Q16557758","pokemonLabel":"Frogadier","pokedexNumber":"657","evolFamilyStmt":"http://www.wikidata.org/entity/Q3716058","evolFamilyStmtLabel":"evolutionary line of Froakie","eggGroupStmt":"http://www.wikidata.org/entity/Q26040640","eggGroupStmtLabel":"Water 1 egg group","type":"http://www.wikidata.org/entity/Q25930495","typeLabel":"water-type Pokémon","colorLabel":"blue","heightLabel":"60"},{"pokemon":"http://www.wikidata.org/entity/Q16562007","pokemonLabel":"Greninja","pokedexNumber":"658","evolFamilyStmt":"http://www.wikidata.org/entity/Q3716058","evolFamilyStmtLabel":"evolutionary line of Froakie","eggGroupStmt":"http://www.wikidata.org/entity/Q26040640","eggGroupStmtLabel":"Water 1 egg group","type":"http://www.wikidata.org/entity/Q25930495","typeLabel":"water-type Pokémon","colorLabel":"blue","heightLabel":"1500","weightLabel":"40"},{"pokemon":"http://www.wikidata.org/entity/Q16562007","pokemonLabel":"Greninja","pokedexNumber":"658","evolFamilyStmt":"http://www.wikidata.org/entity/Q3716058","evolFamilyStmtLabel":"evolutionary line of Froakie","eggGroupStmt":"http://www.wikidata.org/entity/Q26040640","eggGroupStmtLabel":"Water 1 egg group","type":"http://www.wikidata.org/entity/Q25930811","typeLabel":"dark-type Pokémon","colorLabel":"blue","heightLabel":"1500","weightLabel":"40"},{"pokemon":"http://www.wikidata.org/entity/Q17589192","pokemonLabel":"Bunnelby","pokedexNumber":"659","evolFamilyStmt":"http://www.wikidata.org/entity/Q99540794","evolFamilyStmtLabel":"Bunnelby and Diggersby","eggGroupStmt":"http://www.wikidata.org/entity/Q26040408","eggGroupStmtLabel":"Field egg group","type":"http://www.wikidata.org/entity/Q25930498","typeLabel":"normal-type Pokémon","colorLabel":"brown","heightLabel":"40","weightLabel":"5"},{"pokemon":"http://www.wikidata.org/entity/Q16549683","pokemonLabel":"Diggersby","pokedexNumber":"660","evolFamilyStmt":"http://www.wikidata.org/entity/Q99540794","evolFamilyStmtLabel":"Bunnelby and Diggersby","eggGroupStmt":"http://www.wikidata.org/entity/Q26040408","eggGroupStmtLabel":"Field egg group","type":"http://www.wikidata.org/entity/Q25930733","typeLabel":"ground-type Pokémon","colorLabel":"brown","heightLabel":"100"},{"pokemon":"http://www.wikidata.org/entity/Q16549683","pokemonLabel":"Diggersby","pokedexNumber":"660","evolFamilyStmt":"http://www.wikidata.org/entity/Q99540794","evolFamilyStmtLabel":"Bunnelby and Diggersby","eggGroupStmt":"http://www.wikidata.org/entity/Q26040408","eggGroupStmtLabel":"Field egg group","type":"http://www.wikidata.org/entity/Q25930498","typeLabel":"normal-type Pokémon","colorLabel":"brown","heightLabel":"100"},{"pokemon":"http://www.wikidata.org/entity/Q13580502","pokemonLabel":"Fletchling","pokedexNumber":"661","evolFamilyStmt":"http://www.wikidata.org/entity/Q99443412","evolFamilyStmtLabel":"evolutionary line of Fletchling","eggGroupStmt":"http://www.wikidata.org/entity/Q26040471","eggGroupStmtLabel":"Flying egg group","type":"http://www.wikidata.org/entity/Q25930493","typeLabel":"flying-type Pokémon","colorLabel":"red","heightLabel":"30"},{"pokemon":"http://www.wikidata.org/entity/Q13580502","pokemonLabel":"Fletchling","pokedexNumber":"661","evolFamilyStmt":"http://www.wikidata.org/entity/Q99443412","evolFamilyStmtLabel":"evolutionary line of Fletchling","eggGroupStmt":"http://www.wikidata.org/entity/Q26040471","eggGroupStmtLabel":"Flying egg group","type":"http://www.wikidata.org/entity/Q25930498","typeLabel":"normal-type Pokémon","colorLabel":"red","heightLabel":"30"},{"pokemon":"http://www.wikidata.org/entity/Q16556291","pokemonLabel":"Fletchinder","pokedexNumber":"662","evolFamilyStmt":"http://www.wikidata.org/entity/Q99443412","evolFamilyStmtLabel":"evolutionary line of Fletchling","eggGroupStmt":"http://www.wikidata.org/entity/Q26040471","eggGroupStmtLabel":"Flying egg group","type":"http://www.wikidata.org/entity/Q25930493","typeLabel":"flying-type Pokémon","colorLabel":"red","heightLabel":"70","weightLabel":"16"},{"pokemon":"http://www.wikidata.org/entity/Q16556291","pokemonLabel":"Fletchinder","pokedexNumber":"662","evolFamilyStmt":"http://www.wikidata.org/entity/Q99443412","evolFamilyStmtLabel":"evolutionary line of Fletchling","eggGroupStmt":"http://www.wikidata.org/entity/Q26040471","eggGroupStmtLabel":"Flying egg group","type":"http://www.wikidata.org/entity/Q25930490","typeLabel":"Q25930490","colorLabel":"red","heightLabel":"70","weightLabel":"16"},{"pokemon":"http://www.wikidata.org/entity/Q16612125","pokemonLabel":"Talonflame","pokedexNumber":"663","evolFamilyStmt":"http://www.wikidata.org/entity/Q99443412","evolFamilyStmtLabel":"evolutionary line of Fletchling","eggGroupStmt":"http://www.wikidata.org/entity/Q26040471","eggGroupStmtLabel":"Flying egg group","type":"http://www.wikidata.org/entity/Q25930493","typeLabel":"flying-type Pokémon","colorLabel":"red","heightLabel":"120"},{"pokemon":"http://www.wikidata.org/entity/Q16612125","pokemonLabel":"Talonflame","pokedexNumber":"663","evolFamilyStmt":"http://www.wikidata.org/entity/Q99443412","evolFamilyStmtLabel":"evolutionary line of Fletchling","eggGroupStmt":"http://www.wikidata.org/entity/Q26040471","eggGroupStmtLabel":"Flying egg group","type":"http://www.wikidata.org/entity/Q25930490","typeLabel":"Q25930490","colorLabel":"red","heightLabel":"120"},{"pokemon":"http://www.wikidata.org/entity/Q13580503","pokemonLabel":"Scatterbug","pokedexNumber":"664","evolFamilyStmt":"http://www.wikidata.org/entity/Q99472003","evolFamilyStmtLabel":"evolutionary line of Scatterbug","eggGroupStmt":"http://www.wikidata.org/entity/Q26040555","eggGroupStmtLabel":"Bug egg group","type":"http://www.wikidata.org/entity/Q25930757","typeLabel":"bug-type Pokémon","colorLabel":"black","heightLabel":"30"},{"pokemon":"http://www.wikidata.org/entity/Q13580504","pokemonLabel":"Spewpa","pokedexNumber":"665","evolFamilyStmt":"http://www.wikidata.org/entity/Q99472003","evolFamilyStmtLabel":"evolutionary line of Scatterbug","eggGroupStmt":"http://www.wikidata.org/entity/Q26040555","eggGroupStmtLabel":"Bug egg group","type":"http://www.wikidata.org/entity/Q25930757","typeLabel":"bug-type Pokémon","colorLabel":"black","heightLabel":"30"},{"pokemon":"http://www.wikidata.org/entity/Q13580505","pokemonLabel":"Vivillon","pokedexNumber":"666","evolFamilyStmt":"http://www.wikidata.org/entity/Q99472003","evolFamilyStmtLabel":"evolutionary line of Scatterbug","eggGroupStmt":"http://www.wikidata.org/entity/Q26040555","eggGroupStmtLabel":"Bug egg group","type":"http://www.wikidata.org/entity/Q25930493","typeLabel":"flying-type Pokémon","colorLabel":"black","heightLabel":"120","weightLabel":"17"},{"pokemon":"http://www.wikidata.org/entity/Q13580505","pokemonLabel":"Vivillon","pokedexNumber":"666","evolFamilyStmt":"http://www.wikidata.org/entity/Q99472003","evolFamilyStmtLabel":"evolutionary line of Scatterbug","eggGroupStmt":"http://www.wikidata.org/entity/Q26040555","eggGroupStmtLabel":"Bug egg group","type":"http://www.wikidata.org/entity/Q25930757","typeLabel":"bug-type Pokémon","colorLabel":"black","heightLabel":"120","weightLabel":"17"},{"pokemon":"http://www.wikidata.org/entity/Q16573026","pokemonLabel":"Litleo","pokedexNumber":"667","evolFamilyStmt":"http://www.wikidata.org/entity/Q99442807","evolFamilyStmtLabel":"Litleo and Pyroar","eggGroupStmt":"http://www.wikidata.org/entity/Q26040408","eggGroupStmtLabel":"Field egg group","type":"http://www.wikidata.org/entity/Q25930498","typeLabel":"normal-type Pokémon","colorLabel":"brown","heightLabel":"60","weightLabel":"135"},{"pokemon":"http://www.wikidata.org/entity/Q16573026","pokemonLabel":"Litleo","pokedexNumber":"667","evolFamilyStmt":"http://www.wikidata.org/entity/Q99442807","evolFamilyStmtLabel":"Litleo and Pyroar","eggGroupStmt":"http://www.wikidata.org/entity/Q26040408","eggGroupStmtLabel":"Field egg group","type":"http://www.wikidata.org/entity/Q25930490","typeLabel":"Q25930490","colorLabel":"brown","heightLabel":"60","weightLabel":"135"},{"pokemon":"http://www.wikidata.org/entity/Q16593136","pokemonLabel":"Pyroar","pokedexNumber":"668","evolFamilyStmt":"http://www.wikidata.org/entity/Q99442807","evolFamilyStmtLabel":"Litleo and Pyroar","eggGroupStmt":"http://www.wikidata.org/entity/Q26040408","eggGroupStmtLabel":"Field egg group","type":"http://www.wikidata.org/entity/Q25930498","typeLabel":"normal-type Pokémon","colorLabel":"brown","heightLabel":"150","weightLabel":"815"},{"pokemon":"http://www.wikidata.org/entity/Q16593136","pokemonLabel":"Pyroar","pokedexNumber":"668","evolFamilyStmt":"http://www.wikidata.org/entity/Q99442807","evolFamilyStmtLabel":"Litleo and Pyroar","eggGroupStmt":"http://www.wikidata.org/entity/Q26040408","eggGroupStmtLabel":"Field egg group","type":"http://www.wikidata.org/entity/Q25930490","typeLabel":"Q25930490","colorLabel":"brown","heightLabel":"150","weightLabel":"815"},{"pokemon":"http://www.wikidata.org/entity/Q16556244","pokemonLabel":"Flabébé","pokedexNumber":"669","evolFamilyStmt":"http://www.wikidata.org/entity/Q99540881","evolFamilyStmtLabel":"evolutionary line of Flabébé","eggGroupStmt":"http://www.wikidata.org/entity/Q26040377","eggGroupStmtLabel":"Fairy egg group","type":"http://www.wikidata.org/entity/Q25930814","typeLabel":"fairy-type Pokémon","colorLabel":"white","heightLabel":"10","weightLabel":"1"},{"pokemon":"http://www.wikidata.org/entity/Q16556294","pokemonLabel":"Floette","pokedexNumber":"670","evolFamilyStmt":"http://www.wikidata.org/entity/Q99540881","evolFamilyStmtLabel":"evolutionary line of Flabébé","eggGroupStmt":"http://www.wikidata.org/entity/Q26040377","eggGroupStmtLabel":"Fairy egg group","type":"http://www.wikidata.org/entity/Q25930814","typeLabel":"fairy-type Pokémon","colorLabel":"white","heightLabel":"20"},{"pokemon":"http://www.wikidata.org/entity/Q16556309","pokemonLabel":"Florges","pokedexNumber":"671","evolFamilyStmt":"http://www.wikidata.org/entity/Q99540881","evolFamilyStmtLabel":"evolutionary line of Flabébé","eggGroupStmt":"http://www.wikidata.org/entity/Q26040377","eggGroupStmtLabel":"Fairy egg group","type":"http://www.wikidata.org/entity/Q25930814","typeLabel":"fairy-type Pokémon","colorLabel":"white","heightLabel":"110","weightLabel":"10"},{"pokemon":"http://www.wikidata.org/entity/Q16606751","pokemonLabel":"Skiddo","pokedexNumber":"672","evolFamilyStmt":"http://www.wikidata.org/entity/Q99569828","evolFamilyStmtLabel":"Skiddo and Gogoat","eggGroupStmt":"http://www.wikidata.org/entity/Q26040408","eggGroupStmtLabel":"Field egg group","type":"http://www.wikidata.org/entity/Q25930653","typeLabel":"grass-type Pokémon","colorLabel":"brown","heightLabel":"90","weightLabel":"31"},{"pokemon":"http://www.wikidata.org/entity/Q16561316","pokemonLabel":"Gogoat","pokedexNumber":"673","evolFamilyStmt":"http://www.wikidata.org/entity/Q99569828","evolFamilyStmtLabel":"Skiddo and Gogoat","eggGroupStmt":"http://www.wikidata.org/entity/Q26040408","eggGroupStmtLabel":"Field egg group","type":"http://www.wikidata.org/entity/Q25930653","typeLabel":"grass-type Pokémon","colorLabel":"brown","heightLabel":"170","weightLabel":"91"},{"pokemon":"http://www.wikidata.org/entity/Q16586691","pokemonLabel":"Pancham","pokedexNumber":"674","evolFamilyStmt":"http://www.wikidata.org/entity/Q99564680","evolFamilyStmtLabel":"Pancham and Pangoro","eggGroupStmt":"http://www.wikidata.org/entity/Q26040408","eggGroupStmtLabel":"Field egg group","type":"http://www.wikidata.org/entity/Q25930532","typeLabel":"fighting-type Pokémon","colorLabel":"white","heightLabel":"60","weightLabel":"8"},{"pokemon":"http://www.wikidata.org/entity/Q16586691","pokemonLabel":"Pancham","pokedexNumber":"674","evolFamilyStmt":"http://www.wikidata.org/entity/Q99564680","evolFamilyStmtLabel":"Pancham and Pangoro","eggGroupStmt":"http://www.wikidata.org/entity/Q26039794","eggGroupStmtLabel":"Human-like egg group","type":"http://www.wikidata.org/entity/Q25930532","typeLabel":"fighting-type Pokémon","colorLabel":"white","heightLabel":"60","weightLabel":"8"},{"pokemon":"http://www.wikidata.org/entity/Q16586713","pokemonLabel":"Pangoro","pokedexNumber":"675","evolFamilyStmt":"http://www.wikidata.org/entity/Q99564680","evolFamilyStmtLabel":"Pancham and Pangoro","eggGroupStmt":"http://www.wikidata.org/entity/Q26040408","eggGroupStmtLabel":"Field egg group","type":"http://www.wikidata.org/entity/Q25930532","typeLabel":"fighting-type Pokémon","colorLabel":"white","heightLabel":"210","weightLabel":"136"},{"pokemon":"http://www.wikidata.org/entity/Q16586713","pokemonLabel":"Pangoro","pokedexNumber":"675","evolFamilyStmt":"http://www.wikidata.org/entity/Q99564680","evolFamilyStmtLabel":"Pancham and Pangoro","eggGroupStmt":"http://www.wikidata.org/entity/Q26039794","eggGroupStmtLabel":"Human-like egg group","type":"http://www.wikidata.org/entity/Q25930532","typeLabel":"fighting-type Pokémon","colorLabel":"white","heightLabel":"210","weightLabel":"136"},{"pokemon":"http://www.wikidata.org/entity/Q16586713","pokemonLabel":"Pangoro","pokedexNumber":"675","evolFamilyStmt":"http://www.wikidata.org/entity/Q99564680","evolFamilyStmtLabel":"Pancham and Pangoro","eggGroupStmt":"http://www.wikidata.org/entity/Q26040408","eggGroupStmtLabel":"Field egg group","type":"http://www.wikidata.org/entity/Q25930811","typeLabel":"dark-type Pokémon","colorLabel":"white","heightLabel":"210","weightLabel":"136"},{"pokemon":"http://www.wikidata.org/entity/Q16586713","pokemonLabel":"Pangoro","pokedexNumber":"675","evolFamilyStmt":"http://www.wikidata.org/entity/Q99564680","evolFamilyStmtLabel":"Pancham and Pangoro","eggGroupStmt":"http://www.wikidata.org/entity/Q26039794","eggGroupStmtLabel":"Human-like egg group","type":"http://www.wikidata.org/entity/Q25930811","typeLabel":"dark-type Pokémon","colorLabel":"white","heightLabel":"210","weightLabel":"136"},{"pokemon":"http://www.wikidata.org/entity/Q16557928","pokemonLabel":"Furfrou","pokedexNumber":"676","eggGroupStmt":"http://www.wikidata.org/entity/Q26040408","eggGroupStmtLabel":"Field egg group","type":"http://www.wikidata.org/entity/Q25930498","typeLabel":"normal-type Pokémon","colorLabel":"white","heightLabel":"120","weightLabel":"28"},{"pokemon":"http://www.wikidata.org/entity/Q16554490","pokemonLabel":"Espurr","pokedexNumber":"677","evolFamilyStmt":"http://www.wikidata.org/entity/Q101125499","evolFamilyStmtLabel":"Espurr and Meowstic","eggGroupStmt":"http://www.wikidata.org/entity/Q26040408","eggGroupStmtLabel":"Field egg group","type":"http://www.wikidata.org/entity/Q25930740","typeLabel":"psychic-type Pokémon","colorLabel":"gray","heightLabel":"30","weightLabel":"35"},{"pokemon":"http://www.wikidata.org/entity/Q16577854","pokemonLabel":"Meowstic","pokedexNumber":"678","evolFamilyStmt":"http://www.wikidata.org/entity/Q101125499","evolFamilyStmtLabel":"Espurr and Meowstic","eggGroupStmt":"http://www.wikidata.org/entity/Q26040408","eggGroupStmtLabel":"Field egg group","type":"http://www.wikidata.org/entity/Q25930740","typeLabel":"psychic-type Pokémon","colorLabel":"white","heightLabel":"60"},{"pokemon":"http://www.wikidata.org/entity/Q16563618","pokemonLabel":"Honedge","pokedexNumber":"679","evolFamilyStmt":"http://www.wikidata.org/entity/Q101132526","evolFamilyStmtLabel":"evolutionary line of Honedge","eggGroupStmt":"http://www.wikidata.org/entity/Q26040497","eggGroupStmtLabel":"Mineral egg group","type":"http://www.wikidata.org/entity/Q25930806","typeLabel":"ghost-type Pokémon","colorLabel":"brown","heightLabel":"80","weightLabel":"2"},{"pokemon":"http://www.wikidata.org/entity/Q16563618","pokemonLabel":"Honedge","pokedexNumber":"679","evolFamilyStmt":"http://www.wikidata.org/entity/Q101132526","evolFamilyStmtLabel":"evolutionary line of Honedge","eggGroupStmt":"http://www.wikidata.org/entity/Q26040497","eggGroupStmtLabel":"Mineral egg group","type":"http://www.wikidata.org/entity/Q25930813","typeLabel":"steel-type Pokémon","colorLabel":"brown","heightLabel":"80","weightLabel":"2"},{"pokemon":"http://www.wikidata.org/entity/Q16550600","pokemonLabel":"Doublade","pokedexNumber":"680","evolFamilyStmt":"http://www.wikidata.org/entity/Q101132526","evolFamilyStmtLabel":"evolutionary line of Honedge","eggGroupStmt":"http://www.wikidata.org/entity/Q26040497","eggGroupStmtLabel":"Mineral egg group","type":"http://www.wikidata.org/entity/Q25930813","typeLabel":"steel-type Pokémon","colorLabel":"brown","heightLabel":"80","weightLabel":"45"},{"pokemon":"http://www.wikidata.org/entity/Q16550600","pokemonLabel":"Doublade","pokedexNumber":"680","evolFamilyStmt":"http://www.wikidata.org/entity/Q101132526","evolFamilyStmtLabel":"evolutionary line of Honedge","eggGroupStmt":"http://www.wikidata.org/entity/Q26040497","eggGroupStmtLabel":"Mineral egg group","type":"http://www.wikidata.org/entity/Q25930806","typeLabel":"ghost-type Pokémon","colorLabel":"brown","heightLabel":"80","weightLabel":"45"},{"pokemon":"http://www.wikidata.org/entity/Q16524649","pokemonLabel":"Aegislash","pokedexNumber":"681","evolFamilyStmt":"http://www.wikidata.org/entity/Q101132526","evolFamilyStmtLabel":"evolutionary line of Honedge","eggGroupStmt":"http://www.wikidata.org/entity/Q26040497","eggGroupStmtLabel":"Mineral egg group","type":"http://www.wikidata.org/entity/Q25930813","typeLabel":"steel-type Pokémon","colorLabel":"brown","heightLabel":"170","weightLabel":"53"},{"pokemon":"http://www.wikidata.org/entity/Q16524649","pokemonLabel":"Aegislash","pokedexNumber":"681","evolFamilyStmt":"http://www.wikidata.org/entity/Q101132526","evolFamilyStmtLabel":"evolutionary line of Honedge","eggGroupStmt":"http://www.wikidata.org/entity/Q26040497","eggGroupStmtLabel":"Mineral egg group","type":"http://www.wikidata.org/entity/Q25930806","typeLabel":"ghost-type Pokémon","colorLabel":"brown","heightLabel":"170","weightLabel":"53"},{"pokemon":"http://www.wikidata.org/entity/Q16608209","pokemonLabel":"Spritzee","pokedexNumber":"682","evolFamilyStmt":"http://www.wikidata.org/entity/Q101252559","evolFamilyStmtLabel":"Spritzee and Aromatisse","eggGroupStmt":"http://www.wikidata.org/entity/Q26040377","eggGroupStmtLabel":"Fairy egg group","type":"http://www.wikidata.org/entity/Q25930814","typeLabel":"fairy-type Pokémon","colorLabel":"pink","heightLabel":"20"},{"pokemon":"http://www.wikidata.org/entity/Q16528660","pokemonLabel":"Aromatisse","pokedexNumber":"683","evolFamilyStmt":"http://www.wikidata.org/entity/Q101252559","evolFamilyStmtLabel":"Spritzee and Aromatisse","eggGroupStmt":"http://www.wikidata.org/entity/Q26040377","eggGroupStmtLabel":"Fairy egg group","type":"http://www.wikidata.org/entity/Q25930814","typeLabel":"fairy-type Pokémon","colorLabel":"pink","heightLabel":"80"},{"pokemon":"http://www.wikidata.org/entity/Q16611675","pokemonLabel":"Swirlix","pokedexNumber":"684","evolFamilyStmt":"http://www.wikidata.org/entity/Q101252562","evolFamilyStmtLabel":"Swirlix and Slurpuff","eggGroupStmt":"http://www.wikidata.org/entity/Q26040377","eggGroupStmtLabel":"Fairy egg group","type":"http://www.wikidata.org/entity/Q25930814","typeLabel":"fairy-type Pokémon","colorLabel":"white","heightLabel":"40"},{"pokemon":"http://www.wikidata.org/entity/Q16606823","pokemonLabel":"Slurpuff","pokedexNumber":"685","evolFamilyStmt":"http://www.wikidata.org/entity/Q101252562","evolFamilyStmtLabel":"Swirlix and Slurpuff","eggGroupStmt":"http://www.wikidata.org/entity/Q26040377","eggGroupStmtLabel":"Fairy egg group","type":"http://www.wikidata.org/entity/Q25930814","typeLabel":"fairy-type Pokémon","colorLabel":"white","heightLabel":"80","weightLabel":"50"},{"pokemon":"http://www.wikidata.org/entity/Q16565842","pokemonLabel":"Inkay","pokedexNumber":"686","evolFamilyStmt":"http://www.wikidata.org/entity/Q101125590","evolFamilyStmtLabel":"Inkay and Malamar","eggGroupStmt":"http://www.wikidata.org/entity/Q26040640","eggGroupStmtLabel":"Water 1 egg group","type":"http://www.wikidata.org/entity/Q25930811","typeLabel":"dark-type Pokémon","colorLabel":"blue","heightLabel":"40"},{"pokemon":"http://www.wikidata.org/entity/Q16565842","pokemonLabel":"Inkay","pokedexNumber":"686","evolFamilyStmt":"http://www.wikidata.org/entity/Q101125590","evolFamilyStmtLabel":"Inkay and Malamar","eggGroupStmt":"http://www.wikidata.org/entity/Q26040596","eggGroupStmtLabel":"Water 2 egg group","type":"http://www.wikidata.org/entity/Q25930811","typeLabel":"dark-type Pokémon","colorLabel":"blue","heightLabel":"40"},{"pokemon":"http://www.wikidata.org/entity/Q16565842","pokemonLabel":"Inkay","pokedexNumber":"686","evolFamilyStmt":"http://www.wikidata.org/entity/Q101125590","evolFamilyStmtLabel":"Inkay and Malamar","eggGroupStmt":"http://www.wikidata.org/entity/Q26040640","eggGroupStmtLabel":"Water 1 egg group","type":"http://www.wikidata.org/entity/Q25930740","typeLabel":"psychic-type Pokémon","colorLabel":"blue","heightLabel":"40"},{"pokemon":"http://www.wikidata.org/entity/Q16565842","pokemonLabel":"Inkay","pokedexNumber":"686","evolFamilyStmt":"http://www.wikidata.org/entity/Q101125590","evolFamilyStmtLabel":"Inkay and Malamar","eggGroupStmt":"http://www.wikidata.org/entity/Q26040596","eggGroupStmtLabel":"Water 2 egg group","type":"http://www.wikidata.org/entity/Q25930740","typeLabel":"psychic-type Pokémon","colorLabel":"blue","heightLabel":"40"},{"pokemon":"http://www.wikidata.org/entity/Q16575150","pokemonLabel":"Malamar","pokedexNumber":"687","evolFamilyStmt":"http://www.wikidata.org/entity/Q101125590","evolFamilyStmtLabel":"Inkay and Malamar","eggGroupStmt":"http://www.wikidata.org/entity/Q26040640","eggGroupStmtLabel":"Water 1 egg group","type":"http://www.wikidata.org/entity/Q25930740","typeLabel":"psychic-type Pokémon","colorLabel":"blue","heightLabel":"150","weightLabel":"47"},{"pokemon":"http://www.wikidata.org/entity/Q16575150","pokemonLabel":"Malamar","pokedexNumber":"687","evolFamilyStmt":"http://www.wikidata.org/entity/Q101125590","evolFamilyStmtLabel":"Inkay and Malamar","eggGroupStmt":"http://www.wikidata.org/entity/Q26040596","eggGroupStmtLabel":"Water 2 egg group","type":"http://www.wikidata.org/entity/Q25930740","typeLabel":"psychic-type Pokémon","colorLabel":"blue","heightLabel":"150","weightLabel":"47"},{"pokemon":"http://www.wikidata.org/entity/Q16575150","pokemonLabel":"Malamar","pokedexNumber":"687","evolFamilyStmt":"http://www.wikidata.org/entity/Q101125590","evolFamilyStmtLabel":"Inkay and Malamar","eggGroupStmt":"http://www.wikidata.org/entity/Q26040640","eggGroupStmtLabel":"Water 1 egg group","type":"http://www.wikidata.org/entity/Q25930811","typeLabel":"dark-type Pokémon","colorLabel":"blue","heightLabel":"150","weightLabel":"47"},{"pokemon":"http://www.wikidata.org/entity/Q16575150","pokemonLabel":"Malamar","pokedexNumber":"687","evolFamilyStmt":"http://www.wikidata.org/entity/Q101125590","evolFamilyStmtLabel":"Inkay and Malamar","eggGroupStmt":"http://www.wikidata.org/entity/Q26040596","eggGroupStmtLabel":"Water 2 egg group","type":"http://www.wikidata.org/entity/Q25930811","typeLabel":"dark-type Pokémon","colorLabel":"blue","heightLabel":"150","weightLabel":"47"},{"pokemon":"http://www.wikidata.org/entity/Q16532642","pokemonLabel":"Binacle","pokedexNumber":"688","evolFamilyStmt":"http://www.wikidata.org/entity/Q101370111","evolFamilyStmtLabel":"Binacle and Barbaracle","eggGroupStmt":"http://www.wikidata.org/entity/Q26040574","eggGroupStmtLabel":"Water 3 egg group","type":"http://www.wikidata.org/entity/Q25930744","typeLabel":"rock-type Pokémon","colorLabel":"brown","heightLabel":"50","weightLabel":"31"},{"pokemon":"http://www.wikidata.org/entity/Q16532642","pokemonLabel":"Binacle","pokedexNumber":"688","evolFamilyStmt":"http://www.wikidata.org/entity/Q101370111","evolFamilyStmtLabel":"Binacle and Barbaracle","eggGroupStmt":"http://www.wikidata.org/entity/Q26040574","eggGroupStmtLabel":"Water 3 egg group","type":"http://www.wikidata.org/entity/Q25930495","typeLabel":"water-type Pokémon","colorLabel":"brown","heightLabel":"50","weightLabel":"31"},{"pokemon":"http://www.wikidata.org/entity/Q16531090","pokemonLabel":"Barbaracle","pokedexNumber":"689","evolFamilyStmt":"http://www.wikidata.org/entity/Q101370111","evolFamilyStmtLabel":"Binacle and Barbaracle","eggGroupStmt":"http://www.wikidata.org/entity/Q26040574","eggGroupStmtLabel":"Water 3 egg group","type":"http://www.wikidata.org/entity/Q25930495","typeLabel":"water-type Pokémon","colorLabel":"brown","heightLabel":"130","weightLabel":"96"},{"pokemon":"http://www.wikidata.org/entity/Q16531090","pokemonLabel":"Barbaracle","pokedexNumber":"689","evolFamilyStmt":"http://www.wikidata.org/entity/Q101370111","evolFamilyStmtLabel":"Binacle and Barbaracle","eggGroupStmt":"http://www.wikidata.org/entity/Q26040574","eggGroupStmtLabel":"Water 3 egg group","type":"http://www.wikidata.org/entity/Q25930744","typeLabel":"rock-type Pokémon","colorLabel":"brown","heightLabel":"130","weightLabel":"96"},{"pokemon":"http://www.wikidata.org/entity/Q16606765","pokemonLabel":"Skrelp","pokedexNumber":"690","evolFamilyStmt":"http://www.wikidata.org/entity/Q99661134","evolFamilyStmtLabel":"Skrelp and Dragalge","eggGroupStmt":"http://www.wikidata.org/entity/Q26040640","eggGroupStmtLabel":"Water 1 egg group","type":"http://www.wikidata.org/entity/Q25930717","typeLabel":"poison-type Pokémon","colorLabel":"brown","heightLabel":"50"},{"pokemon":"http://www.wikidata.org/entity/Q16606765","pokemonLabel":"Skrelp","pokedexNumber":"690","evolFamilyStmt":"http://www.wikidata.org/entity/Q99661134","evolFamilyStmtLabel":"Skrelp and Dragalge","eggGroupStmt":"http://www.wikidata.org/entity/Q26040142","eggGroupStmtLabel":"Dragon egg group","type":"http://www.wikidata.org/entity/Q25930717","typeLabel":"poison-type Pokémon","colorLabel":"brown","heightLabel":"50"},{"pokemon":"http://www.wikidata.org/entity/Q16606765","pokemonLabel":"Skrelp","pokedexNumber":"690","evolFamilyStmt":"http://www.wikidata.org/entity/Q99661134","evolFamilyStmtLabel":"Skrelp and Dragalge","eggGroupStmt":"http://www.wikidata.org/entity/Q26040640","eggGroupStmtLabel":"Water 1 egg group","type":"http://www.wikidata.org/entity/Q25930495","typeLabel":"water-type Pokémon","colorLabel":"brown","heightLabel":"50"},{"pokemon":"http://www.wikidata.org/entity/Q16606765","pokemonLabel":"Skrelp","pokedexNumber":"690","evolFamilyStmt":"http://www.wikidata.org/entity/Q99661134","evolFamilyStmtLabel":"Skrelp and Dragalge","eggGroupStmt":"http://www.wikidata.org/entity/Q26040142","eggGroupStmtLabel":"Dragon egg group","type":"http://www.wikidata.org/entity/Q25930495","typeLabel":"water-type Pokémon","colorLabel":"brown","heightLabel":"50"},{"pokemon":"http://www.wikidata.org/entity/Q16550650","pokemonLabel":"Dragalge","pokedexNumber":"691","evolFamilyStmt":"http://www.wikidata.org/entity/Q99661134","evolFamilyStmtLabel":"Skrelp and Dragalge","eggGroupStmt":"http://www.wikidata.org/entity/Q26040640","eggGroupStmtLabel":"Water 1 egg group","type":"http://www.wikidata.org/entity/Q25930759","typeLabel":"dragon-type Pokémon","colorLabel":"brown","heightLabel":"180"},{"pokemon":"http://www.wikidata.org/entity/Q16550650","pokemonLabel":"Dragalge","pokedexNumber":"691","evolFamilyStmt":"http://www.wikidata.org/entity/Q99661134","evolFamilyStmtLabel":"Skrelp and Dragalge","eggGroupStmt":"http://www.wikidata.org/entity/Q26040142","eggGroupStmtLabel":"Dragon egg group","type":"http://www.wikidata.org/entity/Q25930759","typeLabel":"dragon-type Pokémon","colorLabel":"brown","heightLabel":"180"},{"pokemon":"http://www.wikidata.org/entity/Q16550650","pokemonLabel":"Dragalge","pokedexNumber":"691","evolFamilyStmt":"http://www.wikidata.org/entity/Q99661134","evolFamilyStmtLabel":"Skrelp and Dragalge","eggGroupStmt":"http://www.wikidata.org/entity/Q26040640","eggGroupStmtLabel":"Water 1 egg group","type":"http://www.wikidata.org/entity/Q25930717","typeLabel":"poison-type Pokémon","colorLabel":"brown","heightLabel":"180"},{"pokemon":"http://www.wikidata.org/entity/Q16550650","pokemonLabel":"Dragalge","pokedexNumber":"691","evolFamilyStmt":"http://www.wikidata.org/entity/Q99661134","evolFamilyStmtLabel":"Skrelp and Dragalge","eggGroupStmt":"http://www.wikidata.org/entity/Q26040142","eggGroupStmtLabel":"Dragon egg group","type":"http://www.wikidata.org/entity/Q25930717","typeLabel":"poison-type Pokémon","colorLabel":"brown","heightLabel":"180"},{"pokemon":"http://www.wikidata.org/entity/Q16542339","pokemonLabel":"Clauncher","pokedexNumber":"692","evolFamilyStmt":"http://www.wikidata.org/entity/Q99526994","evolFamilyStmtLabel":"Clauncher and Clawitzer","eggGroupStmt":"http://www.wikidata.org/entity/Q26040640","eggGroupStmtLabel":"Water 1 egg group","type":"http://www.wikidata.org/entity/Q25930495","typeLabel":"water-type Pokémon","colorLabel":"blue","heightLabel":"50"},{"pokemon":"http://www.wikidata.org/entity/Q16542339","pokemonLabel":"Clauncher","pokedexNumber":"692","evolFamilyStmt":"http://www.wikidata.org/entity/Q99526994","evolFamilyStmtLabel":"Clauncher and Clawitzer","eggGroupStmt":"http://www.wikidata.org/entity/Q26040574","eggGroupStmtLabel":"Water 3 egg group","type":"http://www.wikidata.org/entity/Q25930495","typeLabel":"water-type Pokémon","colorLabel":"blue","heightLabel":"50"},{"pokemon":"http://www.wikidata.org/entity/Q16542347","pokemonLabel":"Clawitzer","pokedexNumber":"693","evolFamilyStmt":"http://www.wikidata.org/entity/Q99526994","evolFamilyStmtLabel":"Clauncher and Clawitzer","eggGroupStmt":"http://www.wikidata.org/entity/Q26040640","eggGroupStmtLabel":"Water 1 egg group","type":"http://www.wikidata.org/entity/Q25930495","typeLabel":"water-type Pokémon","colorLabel":"blue","heightLabel":"130","weightLabel":"353"},{"pokemon":"http://www.wikidata.org/entity/Q16542347","pokemonLabel":"Clawitzer","pokedexNumber":"693","evolFamilyStmt":"http://www.wikidata.org/entity/Q99526994","evolFamilyStmtLabel":"Clauncher and Clawitzer","eggGroupStmt":"http://www.wikidata.org/entity/Q26040574","eggGroupStmtLabel":"Water 3 egg group","type":"http://www.wikidata.org/entity/Q25930495","typeLabel":"water-type Pokémon","colorLabel":"blue","heightLabel":"130","weightLabel":"353"},{"pokemon":"http://www.wikidata.org/entity/Q16563082","pokemonLabel":"Helioptile","pokedexNumber":"694","evolFamilyStmt":"http://www.wikidata.org/entity/Q99540787","evolFamilyStmtLabel":"Helioptile and Heliolisk","eggGroupStmt":"http://www.wikidata.org/entity/Q26040142","eggGroupStmtLabel":"Dragon egg group","type":"http://www.wikidata.org/entity/Q25930498","typeLabel":"normal-type Pokémon","colorLabel":"yellow","heightLabel":"50","weightLabel":"6"},{"pokemon":"http://www.wikidata.org/entity/Q16563082","pokemonLabel":"Helioptile","pokedexNumber":"694","evolFamilyStmt":"http://www.wikidata.org/entity/Q99540787","evolFamilyStmtLabel":"Helioptile and Heliolisk","eggGroupStmt":"http://www.wikidata.org/entity/Q24231890","eggGroupStmtLabel":"Monster egg group","type":"http://www.wikidata.org/entity/Q25930498","typeLabel":"normal-type Pokémon","colorLabel":"yellow","heightLabel":"50","weightLabel":"6"},{"pokemon":"http://www.wikidata.org/entity/Q16563082","pokemonLabel":"Helioptile","pokedexNumber":"694","evolFamilyStmt":"http://www.wikidata.org/entity/Q99540787","evolFamilyStmtLabel":"Helioptile and Heliolisk","eggGroupStmt":"http://www.wikidata.org/entity/Q26040142","eggGroupStmtLabel":"Dragon egg group","type":"http://www.wikidata.org/entity/Q25930719","typeLabel":"electric-type Pokémon","colorLabel":"yellow","heightLabel":"50","weightLabel":"6"},{"pokemon":"http://www.wikidata.org/entity/Q16563082","pokemonLabel":"Helioptile","pokedexNumber":"694","evolFamilyStmt":"http://www.wikidata.org/entity/Q99540787","evolFamilyStmtLabel":"Helioptile and Heliolisk","eggGroupStmt":"http://www.wikidata.org/entity/Q24231890","eggGroupStmtLabel":"Monster egg group","type":"http://www.wikidata.org/entity/Q25930719","typeLabel":"electric-type Pokémon","colorLabel":"yellow","heightLabel":"50","weightLabel":"6"},{"pokemon":"http://www.wikidata.org/entity/Q16563079","pokemonLabel":"Heliolisk","pokedexNumber":"695","evolFamilyStmt":"http://www.wikidata.org/entity/Q99540787","evolFamilyStmtLabel":"Helioptile and Heliolisk","eggGroupStmt":"http://www.wikidata.org/entity/Q26040142","eggGroupStmtLabel":"Dragon egg group","type":"http://www.wikidata.org/entity/Q25930498","typeLabel":"normal-type Pokémon","colorLabel":"yellow","heightLabel":"100","weightLabel":"21"},{"pokemon":"http://www.wikidata.org/entity/Q16563079","pokemonLabel":"Heliolisk","pokedexNumber":"695","evolFamilyStmt":"http://www.wikidata.org/entity/Q99540787","evolFamilyStmtLabel":"Helioptile and Heliolisk","eggGroupStmt":"http://www.wikidata.org/entity/Q24231890","eggGroupStmtLabel":"Monster egg group","type":"http://www.wikidata.org/entity/Q25930498","typeLabel":"normal-type Pokémon","colorLabel":"yellow","heightLabel":"100","weightLabel":"21"},{"pokemon":"http://www.wikidata.org/entity/Q16563079","pokemonLabel":"Heliolisk","pokedexNumber":"695","evolFamilyStmt":"http://www.wikidata.org/entity/Q99540787","evolFamilyStmtLabel":"Helioptile and Heliolisk","eggGroupStmt":"http://www.wikidata.org/entity/Q26040142","eggGroupStmtLabel":"Dragon egg group","type":"http://www.wikidata.org/entity/Q25930719","typeLabel":"electric-type Pokémon","colorLabel":"yellow","heightLabel":"100","weightLabel":"21"},{"pokemon":"http://www.wikidata.org/entity/Q16563079","pokemonLabel":"Heliolisk","pokedexNumber":"695","evolFamilyStmt":"http://www.wikidata.org/entity/Q99540787","evolFamilyStmtLabel":"Helioptile and Heliolisk","eggGroupStmt":"http://www.wikidata.org/entity/Q24231890","eggGroupStmtLabel":"Monster egg group","type":"http://www.wikidata.org/entity/Q25930719","typeLabel":"electric-type Pokémon","colorLabel":"yellow","heightLabel":"100","weightLabel":"21"},{"pokemon":"http://www.wikidata.org/entity/Q16618518","pokemonLabel":"Tyrunt","pokedexNumber":"696","evolFamilyStmt":"http://www.wikidata.org/entity/Q101252475","evolFamilyStmtLabel":"Tyrunt and Tyrantrum","eggGroupStmt":"http://www.wikidata.org/entity/Q26040142","eggGroupStmtLabel":"Dragon egg group","type":"http://www.wikidata.org/entity/Q25930759","typeLabel":"dragon-type Pokémon","colorLabel":"brown","heightLabel":"80","weightLabel":"26"},{"pokemon":"http://www.wikidata.org/entity/Q16618518","pokemonLabel":"Tyrunt","pokedexNumber":"696","evolFamilyStmt":"http://www.wikidata.org/entity/Q101252475","evolFamilyStmtLabel":"Tyrunt and Tyrantrum","eggGroupStmt":"http://www.wikidata.org/entity/Q24231890","eggGroupStmtLabel":"Monster egg group","type":"http://www.wikidata.org/entity/Q25930759","typeLabel":"dragon-type Pokémon","colorLabel":"brown","heightLabel":"80","weightLabel":"26"},{"pokemon":"http://www.wikidata.org/entity/Q16618518","pokemonLabel":"Tyrunt","pokedexNumber":"696","evolFamilyStmt":"http://www.wikidata.org/entity/Q101252475","evolFamilyStmtLabel":"Tyrunt and Tyrantrum","eggGroupStmt":"http://www.wikidata.org/entity/Q26040142","eggGroupStmtLabel":"Dragon egg group","type":"http://www.wikidata.org/entity/Q25930744","typeLabel":"rock-type Pokémon","colorLabel":"brown","heightLabel":"80","weightLabel":"26"},{"pokemon":"http://www.wikidata.org/entity/Q16618518","pokemonLabel":"Tyrunt","pokedexNumber":"696","evolFamilyStmt":"http://www.wikidata.org/entity/Q101252475","evolFamilyStmtLabel":"Tyrunt and Tyrantrum","eggGroupStmt":"http://www.wikidata.org/entity/Q24231890","eggGroupStmtLabel":"Monster egg group","type":"http://www.wikidata.org/entity/Q25930744","typeLabel":"rock-type Pokémon","colorLabel":"brown","heightLabel":"80","weightLabel":"26"},{"pokemon":"http://www.wikidata.org/entity/Q16618512","pokemonLabel":"Tyrantrum","pokedexNumber":"697","evolFamilyStmt":"http://www.wikidata.org/entity/Q101252475","evolFamilyStmtLabel":"Tyrunt and Tyrantrum","eggGroupStmt":"http://www.wikidata.org/entity/Q26040142","eggGroupStmtLabel":"Dragon egg group","type":"http://www.wikidata.org/entity/Q25930744","typeLabel":"rock-type Pokémon","colorLabel":"red","heightLabel":"250","weightLabel":"270"},{"pokemon":"http://www.wikidata.org/entity/Q16618512","pokemonLabel":"Tyrantrum","pokedexNumber":"697","evolFamilyStmt":"http://www.wikidata.org/entity/Q101252475","evolFamilyStmtLabel":"Tyrunt and Tyrantrum","eggGroupStmt":"http://www.wikidata.org/entity/Q24231890","eggGroupStmtLabel":"Monster egg group","type":"http://www.wikidata.org/entity/Q25930744","typeLabel":"rock-type Pokémon","colorLabel":"red","heightLabel":"250","weightLabel":"270"},{"pokemon":"http://www.wikidata.org/entity/Q16618512","pokemonLabel":"Tyrantrum","pokedexNumber":"697","evolFamilyStmt":"http://www.wikidata.org/entity/Q101252475","evolFamilyStmtLabel":"Tyrunt and Tyrantrum","eggGroupStmt":"http://www.wikidata.org/entity/Q26040142","eggGroupStmtLabel":"Dragon egg group","type":"http://www.wikidata.org/entity/Q25930759","typeLabel":"dragon-type Pokémon","colorLabel":"red","heightLabel":"250","weightLabel":"270"},{"pokemon":"http://www.wikidata.org/entity/Q16618512","pokemonLabel":"Tyrantrum","pokedexNumber":"697","evolFamilyStmt":"http://www.wikidata.org/entity/Q101252475","evolFamilyStmtLabel":"Tyrunt and Tyrantrum","eggGroupStmt":"http://www.wikidata.org/entity/Q24231890","eggGroupStmtLabel":"Monster egg group","type":"http://www.wikidata.org/entity/Q25930759","typeLabel":"dragon-type Pokémon","colorLabel":"red","heightLabel":"250","weightLabel":"270"},{"pokemon":"http://www.wikidata.org/entity/Q16525794","pokemonLabel":"Amaura","pokedexNumber":"698","evolFamilyStmt":"http://www.wikidata.org/entity/Q101372582","evolFamilyStmtLabel":"Amaura and Aurorus","eggGroupStmt":"http://www.wikidata.org/entity/Q24231890","eggGroupStmtLabel":"Monster egg group","type":"http://www.wikidata.org/entity/Q25930744","typeLabel":"rock-type Pokémon","colorLabel":"blue","heightLabel":"130"},{"pokemon":"http://www.wikidata.org/entity/Q16525794","pokemonLabel":"Amaura","pokedexNumber":"698","evolFamilyStmt":"http://www.wikidata.org/entity/Q101372582","evolFamilyStmtLabel":"Amaura and Aurorus","eggGroupStmt":"http://www.wikidata.org/entity/Q24231890","eggGroupStmtLabel":"Monster egg group","type":"http://www.wikidata.org/entity/Q25930752","typeLabel":"ice-type Pokémon","colorLabel":"blue","heightLabel":"130"},{"pokemon":"http://www.wikidata.org/entity/Q17622057","pokemonLabel":"Aurorus","pokedexNumber":"699","evolFamilyStmt":"http://www.wikidata.org/entity/Q101372582","evolFamilyStmtLabel":"Amaura and Aurorus","eggGroupStmt":"http://www.wikidata.org/entity/Q24231890","eggGroupStmtLabel":"Monster egg group","type":"http://www.wikidata.org/entity/Q25930752","typeLabel":"ice-type Pokémon","colorLabel":"blue","heightLabel":"270","weightLabel":"225"},{"pokemon":"http://www.wikidata.org/entity/Q17622057","pokemonLabel":"Aurorus","pokedexNumber":"699","evolFamilyStmt":"http://www.wikidata.org/entity/Q101372582","evolFamilyStmtLabel":"Amaura and Aurorus","eggGroupStmt":"http://www.wikidata.org/entity/Q24231890","eggGroupStmtLabel":"Monster egg group","type":"http://www.wikidata.org/entity/Q25930744","typeLabel":"rock-type Pokémon","colorLabel":"blue","heightLabel":"270","weightLabel":"225"},{"pokemon":"http://www.wikidata.org/entity/Q4502668","pokemonLabel":"Sylveon","pokedexNumber":"700","evolFamilyStmt":"http://www.wikidata.org/entity/Q12357586","evolFamilyStmtLabel":"evolutionary line of Eevee","eggGroupStmt":"http://www.wikidata.org/entity/Q26040408","eggGroupStmtLabel":"Field egg group","genderRatioStmt":"http://www.wikidata.org/entity/Q116752952","grStmtLabel":"87.5% male, 12.5% female gender ratio","type":"http://www.wikidata.org/entity/Q25930814","typeLabel":"fairy-type Pokémon","colorLabel":"blue","heightLabel":"100","weightLabel":"23.5","shape":"http://www.wikidata.org/entity/Q116751762","shapeLabel":"Pokémon with a quadruped body"},{"pokemon":"http://www.wikidata.org/entity/Q4502668","pokemonLabel":"Sylveon","pokedexNumber":"700","evolFamilyStmt":"http://www.wikidata.org/entity/Q12357586","evolFamilyStmtLabel":"evolutionary line of Eevee","eggGroupStmt":"http://www.wikidata.org/entity/Q26040408","eggGroupStmtLabel":"Field egg group","genderRatioStmt":"http://www.wikidata.org/entity/Q116752952","grStmtLabel":"87.5% male, 12.5% female gender ratio","type":"http://www.wikidata.org/entity/Q25930814","typeLabel":"fairy-type Pokémon","colorLabel":"white","heightLabel":"100","weightLabel":"23.5","shape":"http://www.wikidata.org/entity/Q116751762","shapeLabel":"Pokémon with a quadruped body"},{"pokemon":"http://www.wikidata.org/entity/Q4502668","pokemonLabel":"Sylveon","pokedexNumber":"700","evolFamilyStmt":"http://www.wikidata.org/entity/Q12357586","evolFamilyStmtLabel":"evolutionary line of Eevee","eggGroupStmt":"http://www.wikidata.org/entity/Q26040408","eggGroupStmtLabel":"Field egg group","genderRatioStmt":"http://www.wikidata.org/entity/Q116752952","grStmtLabel":"87.5% male, 12.5% female gender ratio","type":"http://www.wikidata.org/entity/Q25930814","typeLabel":"fairy-type Pokémon","colorLabel":"pink","heightLabel":"100","weightLabel":"23.5","shape":"http://www.wikidata.org/entity/Q116751762","shapeLabel":"Pokémon with a quadruped body"},{"pokemon":"http://www.wikidata.org/entity/Q16562897","pokemonLabel":"Hawlucha","pokedexNumber":"701","eggGroupStmt":"http://www.wikidata.org/entity/Q26039794","eggGroupStmtLabel":"Human-like egg group","type":"http://www.wikidata.org/entity/Q25930532","typeLabel":"fighting-type Pokémon","colorLabel":"green","heightLabel":"80"},{"pokemon":"http://www.wikidata.org/entity/Q16562897","pokemonLabel":"Hawlucha","pokedexNumber":"701","eggGroupStmt":"http://www.wikidata.org/entity/Q26039794","eggGroupStmtLabel":"Human-like egg group","type":"http://www.wikidata.org/entity/Q25930493","typeLabel":"flying-type Pokémon","colorLabel":"green","heightLabel":"80"},{"pokemon":"http://www.wikidata.org/entity/Q16549046","pokemonLabel":"Dedenne","pokedexNumber":"702","eggGroupStmt":"http://www.wikidata.org/entity/Q26040408","eggGroupStmtLabel":"Field egg group","type":"http://www.wikidata.org/entity/Q25930719","typeLabel":"electric-type Pokémon","colorLabel":"yellow","heightLabel":"20"},{"pokemon":"http://www.wikidata.org/entity/Q16549046","pokemonLabel":"Dedenne","pokedexNumber":"702","eggGroupStmt":"http://www.wikidata.org/entity/Q26040377","eggGroupStmtLabel":"Fairy egg group","type":"http://www.wikidata.org/entity/Q25930719","typeLabel":"electric-type Pokémon","colorLabel":"yellow","heightLabel":"20"},{"pokemon":"http://www.wikidata.org/entity/Q16549046","pokemonLabel":"Dedenne","pokedexNumber":"702","eggGroupStmt":"http://www.wikidata.org/entity/Q26040408","eggGroupStmtLabel":"Field egg group","type":"http://www.wikidata.org/entity/Q25930814","typeLabel":"fairy-type Pokémon","colorLabel":"yellow","heightLabel":"20"},{"pokemon":"http://www.wikidata.org/entity/Q16549046","pokemonLabel":"Dedenne","pokedexNumber":"702","eggGroupStmt":"http://www.wikidata.org/entity/Q26040377","eggGroupStmtLabel":"Fairy egg group","type":"http://www.wikidata.org/entity/Q25930814","typeLabel":"fairy-type Pokémon","colorLabel":"yellow","heightLabel":"20"},{"pokemon":"http://www.wikidata.org/entity/Q16536668","pokemonLabel":"Carbink","pokedexNumber":"703","eggGroupStmt":"http://www.wikidata.org/entity/Q26040497","eggGroupStmtLabel":"Mineral egg group","type":"http://www.wikidata.org/entity/Q25930744","typeLabel":"rock-type Pokémon","colorLabel":"gray","heightLabel":"30"},{"pokemon":"http://www.wikidata.org/entity/Q16536668","pokemonLabel":"Carbink","pokedexNumber":"703","eggGroupStmt":"http://www.wikidata.org/entity/Q26040377","eggGroupStmtLabel":"Fairy egg group","type":"http://www.wikidata.org/entity/Q25930744","typeLabel":"rock-type Pokémon","colorLabel":"gray","heightLabel":"30"},{"pokemon":"http://www.wikidata.org/entity/Q16536668","pokemonLabel":"Carbink","pokedexNumber":"703","eggGroupStmt":"http://www.wikidata.org/entity/Q26040071","eggGroupStmtLabel":"Gender unknown egg group","type":"http://www.wikidata.org/entity/Q25930744","typeLabel":"rock-type Pokémon","colorLabel":"gray","heightLabel":"30"},{"pokemon":"http://www.wikidata.org/entity/Q16536668","pokemonLabel":"Carbink","pokedexNumber":"703","eggGroupStmt":"http://www.wikidata.org/entity/Q26040497","eggGroupStmtLabel":"Mineral egg group","type":"http://www.wikidata.org/entity/Q25930814","typeLabel":"fairy-type Pokémon","colorLabel":"gray","heightLabel":"30"},{"pokemon":"http://www.wikidata.org/entity/Q16536668","pokemonLabel":"Carbink","pokedexNumber":"703","eggGroupStmt":"http://www.wikidata.org/entity/Q26040377","eggGroupStmtLabel":"Fairy egg group","type":"http://www.wikidata.org/entity/Q25930814","typeLabel":"fairy-type Pokémon","colorLabel":"gray","heightLabel":"30"},{"pokemon":"http://www.wikidata.org/entity/Q16536668","pokemonLabel":"Carbink","pokedexNumber":"703","eggGroupStmt":"http://www.wikidata.org/entity/Q26040071","eggGroupStmtLabel":"Gender unknown egg group","type":"http://www.wikidata.org/entity/Q25930814","typeLabel":"fairy-type Pokémon","colorLabel":"gray","heightLabel":"30"},{"pokemon":"http://www.wikidata.org/entity/Q16561444","pokemonLabel":"Goomy","pokedexNumber":"704","evolFamilyStmt":"http://www.wikidata.org/entity/Q101133182","evolFamilyStmtLabel":"evolutionary line of Goomy","eggGroupStmt":"http://www.wikidata.org/entity/Q26040142","eggGroupStmtLabel":"Dragon egg group","type":"http://www.wikidata.org/entity/Q25930759","typeLabel":"dragon-type Pokémon","colorLabel":"purple","heightLabel":"30"},{"pokemon":"http://www.wikidata.org/entity/Q16606799","pokemonLabel":"Sliggoo","pokedexNumber":"705","evolFamilyStmt":"http://www.wikidata.org/entity/Q101133182","evolFamilyStmtLabel":"evolutionary line of Goomy","eggGroupStmt":"http://www.wikidata.org/entity/Q26040142","eggGroupStmtLabel":"Dragon egg group","type":"http://www.wikidata.org/entity/Q25930759","typeLabel":"dragon-type Pokémon","colorLabel":"purple","heightLabel":"80"},{"pokemon":"http://www.wikidata.org/entity/Q16561438","pokemonLabel":"Goodra","pokedexNumber":"706","evolFamilyStmt":"http://www.wikidata.org/entity/Q101133182","evolFamilyStmtLabel":"evolutionary line of Goomy","eggGroupStmt":"http://www.wikidata.org/entity/Q26040142","eggGroupStmtLabel":"Dragon egg group","type":"http://www.wikidata.org/entity/Q25930759","typeLabel":"dragon-type Pokémon","heightLabel":"200","weightLabel":"150"},{"pokemon":"http://www.wikidata.org/entity/Q16203349","pokemonLabel":"Klefki","pokedexNumber":"707","eggGroupStmt":"http://www.wikidata.org/entity/Q26040497","eggGroupStmtLabel":"Mineral egg group","type":"http://www.wikidata.org/entity/Q25930813","typeLabel":"steel-type Pokémon","colorLabel":"gray","heightLabel":"20","weightLabel":"3"},{"pokemon":"http://www.wikidata.org/entity/Q16203349","pokemonLabel":"Klefki","pokedexNumber":"707","eggGroupStmt":"http://www.wikidata.org/entity/Q26040497","eggGroupStmtLabel":"Mineral egg group","type":"http://www.wikidata.org/entity/Q25930814","typeLabel":"fairy-type Pokémon","colorLabel":"gray","heightLabel":"20","weightLabel":"3"},{"pokemon":"http://www.wikidata.org/entity/Q16589888","pokemonLabel":"Phantump","pokedexNumber":"708","evolFamilyStmt":"http://www.wikidata.org/entity/Q99570522","evolFamilyStmtLabel":"Phantump and Trevenant","eggGroupStmt":"http://www.wikidata.org/entity/Q26040453","eggGroupStmtLabel":"Amorphous egg group","type":"http://www.wikidata.org/entity/Q25930653","typeLabel":"grass-type Pokémon","colorLabel":"brown","heightLabel":"40","weightLabel":"7"},{"pokemon":"http://www.wikidata.org/entity/Q16589888","pokemonLabel":"Phantump","pokedexNumber":"708","evolFamilyStmt":"http://www.wikidata.org/entity/Q99570522","evolFamilyStmtLabel":"Phantump and Trevenant","eggGroupStmt":"http://www.wikidata.org/entity/Q24231984","eggGroupStmtLabel":"Grass egg group","type":"http://www.wikidata.org/entity/Q25930653","typeLabel":"grass-type Pokémon","colorLabel":"brown","heightLabel":"40","weightLabel":"7"},{"pokemon":"http://www.wikidata.org/entity/Q16589888","pokemonLabel":"Phantump","pokedexNumber":"708","evolFamilyStmt":"http://www.wikidata.org/entity/Q99570522","evolFamilyStmtLabel":"Phantump and Trevenant","eggGroupStmt":"http://www.wikidata.org/entity/Q26040453","eggGroupStmtLabel":"Amorphous egg group","type":"http://www.wikidata.org/entity/Q25930806","typeLabel":"ghost-type Pokémon","colorLabel":"brown","heightLabel":"40","weightLabel":"7"},{"pokemon":"http://www.wikidata.org/entity/Q16589888","pokemonLabel":"Phantump","pokedexNumber":"708","evolFamilyStmt":"http://www.wikidata.org/entity/Q99570522","evolFamilyStmtLabel":"Phantump and Trevenant","eggGroupStmt":"http://www.wikidata.org/entity/Q24231984","eggGroupStmtLabel":"Grass egg group","type":"http://www.wikidata.org/entity/Q25930806","typeLabel":"ghost-type Pokémon","colorLabel":"brown","heightLabel":"40","weightLabel":"7"},{"pokemon":"http://www.wikidata.org/entity/Q16617658","pokemonLabel":"Trevenant","pokedexNumber":"709","evolFamilyStmt":"http://www.wikidata.org/entity/Q99570522","evolFamilyStmtLabel":"Phantump and Trevenant","eggGroupStmt":"http://www.wikidata.org/entity/Q26040453","eggGroupStmtLabel":"Amorphous egg group","type":"http://www.wikidata.org/entity/Q25930806","typeLabel":"ghost-type Pokémon","colorLabel":"brown","heightLabel":"150","weightLabel":"71"},{"pokemon":"http://www.wikidata.org/entity/Q16617658","pokemonLabel":"Trevenant","pokedexNumber":"709","evolFamilyStmt":"http://www.wikidata.org/entity/Q99570522","evolFamilyStmtLabel":"Phantump and Trevenant","eggGroupStmt":"http://www.wikidata.org/entity/Q24231984","eggGroupStmtLabel":"Grass egg group","type":"http://www.wikidata.org/entity/Q25930806","typeLabel":"ghost-type Pokémon","colorLabel":"brown","heightLabel":"150","weightLabel":"71"},{"pokemon":"http://www.wikidata.org/entity/Q16617658","pokemonLabel":"Trevenant","pokedexNumber":"709","evolFamilyStmt":"http://www.wikidata.org/entity/Q99570522","evolFamilyStmtLabel":"Phantump and Trevenant","eggGroupStmt":"http://www.wikidata.org/entity/Q26040453","eggGroupStmtLabel":"Amorphous egg group","type":"http://www.wikidata.org/entity/Q25930653","typeLabel":"grass-type Pokémon","colorLabel":"brown","heightLabel":"150","weightLabel":"71"},{"pokemon":"http://www.wikidata.org/entity/Q16617658","pokemonLabel":"Trevenant","pokedexNumber":"709","evolFamilyStmt":"http://www.wikidata.org/entity/Q99570522","evolFamilyStmtLabel":"Phantump and Trevenant","eggGroupStmt":"http://www.wikidata.org/entity/Q24231984","eggGroupStmtLabel":"Grass egg group","type":"http://www.wikidata.org/entity/Q25930653","typeLabel":"grass-type Pokémon","colorLabel":"brown","heightLabel":"150","weightLabel":"71"},{"pokemon":"http://www.wikidata.org/entity/Q16592958","pokemonLabel":"Pumpkaboo","pokedexNumber":"710","evolFamilyStmt":"http://www.wikidata.org/entity/Q99570554","evolFamilyStmtLabel":"Pumpkaboo and Gourgeist","eggGroupStmt":"http://www.wikidata.org/entity/Q26040453","eggGroupStmtLabel":"Amorphous egg group","type":"http://www.wikidata.org/entity/Q25930653","typeLabel":"grass-type Pokémon","colorLabel":"brown","heightLabel":"40","weightLabel":"5"},{"pokemon":"http://www.wikidata.org/entity/Q16592958","pokemonLabel":"Pumpkaboo","pokedexNumber":"710","evolFamilyStmt":"http://www.wikidata.org/entity/Q99570554","evolFamilyStmtLabel":"Pumpkaboo and Gourgeist","eggGroupStmt":"http://www.wikidata.org/entity/Q26040453","eggGroupStmtLabel":"Amorphous egg group","type":"http://www.wikidata.org/entity/Q25930806","typeLabel":"ghost-type Pokémon","colorLabel":"brown","heightLabel":"40","weightLabel":"5"},{"pokemon":"http://www.wikidata.org/entity/Q16561499","pokemonLabel":"Gourgeist","pokedexNumber":"711","evolFamilyStmt":"http://www.wikidata.org/entity/Q99570554","evolFamilyStmtLabel":"Pumpkaboo and Gourgeist","eggGroupStmt":"http://www.wikidata.org/entity/Q26040453","eggGroupStmtLabel":"Amorphous egg group","type":"http://www.wikidata.org/entity/Q25930806","typeLabel":"ghost-type Pokémon","colorLabel":"brown","heightLabel":"90"},{"pokemon":"http://www.wikidata.org/entity/Q16561499","pokemonLabel":"Gourgeist","pokedexNumber":"711","evolFamilyStmt":"http://www.wikidata.org/entity/Q99570554","evolFamilyStmtLabel":"Pumpkaboo and Gourgeist","eggGroupStmt":"http://www.wikidata.org/entity/Q26040453","eggGroupStmtLabel":"Amorphous egg group","type":"http://www.wikidata.org/entity/Q25930653","typeLabel":"grass-type Pokémon","colorLabel":"brown","heightLabel":"90"},{"pokemon":"http://www.wikidata.org/entity/Q16532081","pokemonLabel":"Bergmite","pokedexNumber":"712","evolFamilyStmt":"http://www.wikidata.org/entity/Q101374746","evolFamilyStmtLabel":"Bergmite and Avalugg","eggGroupStmt":"http://www.wikidata.org/entity/Q24231890","eggGroupStmtLabel":"Monster egg group","type":"http://www.wikidata.org/entity/Q25930752","typeLabel":"ice-type Pokémon","colorLabel":"blue","heightLabel":"100","weightLabel":"99.5"},{"pokemon":"http://www.wikidata.org/entity/Q16530193","pokemonLabel":"Avalugg","pokedexNumber":"713","evolFamilyStmt":"http://www.wikidata.org/entity/Q101374746","evolFamilyStmtLabel":"Bergmite and Avalugg","eggGroupStmt":"http://www.wikidata.org/entity/Q26040497","eggGroupStmtLabel":"Mineral egg group","type":"http://www.wikidata.org/entity/Q25930752","typeLabel":"ice-type Pokémon","colorLabel":"blue","heightLabel":"200","weightLabel":"505"},{"pokemon":"http://www.wikidata.org/entity/Q16530193","pokemonLabel":"Avalugg","pokedexNumber":"713","evolFamilyStmt":"http://www.wikidata.org/entity/Q101374746","evolFamilyStmtLabel":"Bergmite and Avalugg","eggGroupStmt":"http://www.wikidata.org/entity/Q24231890","eggGroupStmtLabel":"Monster egg group","type":"http://www.wikidata.org/entity/Q25930752","typeLabel":"ice-type Pokémon","colorLabel":"blue","heightLabel":"200","weightLabel":"505"},{"pokemon":"http://www.wikidata.org/entity/Q16582772","pokemonLabel":"Noibat","pokedexNumber":"714","evolFamilyStmt":"http://www.wikidata.org/entity/Q99471975","evolFamilyStmtLabel":"Noibat and Noivern","eggGroupStmt":"http://www.wikidata.org/entity/Q26040471","eggGroupStmtLabel":"Flying egg group","type":"http://www.wikidata.org/entity/Q25930493","typeLabel":"flying-type Pokémon","colorLabel":"purple","heightLabel":"50","weightLabel":"8"},{"pokemon":"http://www.wikidata.org/entity/Q16582772","pokemonLabel":"Noibat","pokedexNumber":"714","evolFamilyStmt":"http://www.wikidata.org/entity/Q99471975","evolFamilyStmtLabel":"Noibat and Noivern","eggGroupStmt":"http://www.wikidata.org/entity/Q26040471","eggGroupStmtLabel":"Flying egg group","type":"http://www.wikidata.org/entity/Q25930759","typeLabel":"dragon-type Pokémon","colorLabel":"purple","heightLabel":"50","weightLabel":"8"},{"pokemon":"http://www.wikidata.org/entity/Q16582774","pokemonLabel":"Noivern","pokedexNumber":"715","evolFamilyStmt":"http://www.wikidata.org/entity/Q99471975","evolFamilyStmtLabel":"Noibat and Noivern","eggGroupStmt":"http://www.wikidata.org/entity/Q26040471","eggGroupStmtLabel":"Flying egg group","type":"http://www.wikidata.org/entity/Q25930759","typeLabel":"dragon-type Pokémon","colorLabel":"purple","heightLabel":"150","weightLabel":"85"},{"pokemon":"http://www.wikidata.org/entity/Q16582774","pokemonLabel":"Noivern","pokedexNumber":"715","evolFamilyStmt":"http://www.wikidata.org/entity/Q99471975","evolFamilyStmtLabel":"Noibat and Noivern","eggGroupStmt":"http://www.wikidata.org/entity/Q26040471","eggGroupStmtLabel":"Flying egg group","type":"http://www.wikidata.org/entity/Q25930493","typeLabel":"flying-type Pokémon","colorLabel":"purple","heightLabel":"150","weightLabel":"85"},{"pokemon":"http://www.wikidata.org/entity/Q12524951","pokemonLabel":"Xerneas","pokedexNumber":"716","eggGroupStmt":"http://www.wikidata.org/entity/Q26040095","eggGroupStmtLabel":"Undiscovered egg group","type":"http://www.wikidata.org/entity/Q25930814","typeLabel":"fairy-type Pokémon","colorLabel":"blue","heightLabel":"300","weightLabel":"215"},{"pokemon":"http://www.wikidata.org/entity/Q12525374","pokemonLabel":"Yveltal","pokedexNumber":"717","eggGroupStmt":"http://www.wikidata.org/entity/Q26040095","eggGroupStmtLabel":"Undiscovered egg group","type":"http://www.wikidata.org/entity/Q25930493","typeLabel":"flying-type Pokémon","colorLabel":"red","heightLabel":"580","weightLabel":"203"},{"pokemon":"http://www.wikidata.org/entity/Q12525374","pokemonLabel":"Yveltal","pokedexNumber":"717","eggGroupStmt":"http://www.wikidata.org/entity/Q26040095","eggGroupStmtLabel":"Undiscovered egg group","type":"http://www.wikidata.org/entity/Q25930811","typeLabel":"dark-type Pokémon","colorLabel":"red","heightLabel":"580","weightLabel":"203"},{"pokemon":"http://www.wikidata.org/entity/Q16623960","pokemonLabel":"Zygarde","pokedexNumber":"718","eggGroupStmt":"http://www.wikidata.org/entity/Q26040095","eggGroupStmtLabel":"Undiscovered egg group","type":"http://www.wikidata.org/entity/Q25930733","typeLabel":"ground-type Pokémon","colorLabel":"green","heightLabel":"500","weightLabel":"305","shape":"http://www.wikidata.org/entity/Q116751792","shapeLabel":"Pokémon with serpentine bodies"},{"pokemon":"http://www.wikidata.org/entity/Q16623960","pokemonLabel":"Zygarde","pokedexNumber":"718","eggGroupStmt":"http://www.wikidata.org/entity/Q26040095","eggGroupStmtLabel":"Undiscovered egg group","type":"http://www.wikidata.org/entity/Q25930759","typeLabel":"dragon-type Pokémon","colorLabel":"green","heightLabel":"500","weightLabel":"305","shape":"http://www.wikidata.org/entity/Q116751792","shapeLabel":"Pokémon with serpentine bodies"},{"pokemon":"http://www.wikidata.org/entity/Q16549476","pokemonLabel":"Diancie","pokedexNumber":"719","eggGroupStmt":"http://www.wikidata.org/entity/Q26040095","eggGroupStmtLabel":"Undiscovered egg group","type":"http://www.wikidata.org/entity/Q25930744","typeLabel":"rock-type Pokémon","colorLabel":"pink","heightLabel":"70","usesStmt":"http://www.wikidata.org/entity/statement/Q16549476-2D757AB6-CB0A-41DC-B364-BC287FA9492B","megaEvolStone":"http://www.wikidata.org/entity/Q56676306","megaEvolStoneLabel":"Diancite"},{"pokemon":"http://www.wikidata.org/entity/Q16549476","pokemonLabel":"Diancie","pokedexNumber":"719","eggGroupStmt":"http://www.wikidata.org/entity/Q26040095","eggGroupStmtLabel":"Undiscovered egg group","type":"http://www.wikidata.org/entity/Q25930740","typeLabel":"psychic-type Pokémon","colorLabel":"pink","heightLabel":"70","usesStmt":"http://www.wikidata.org/entity/statement/Q16549476-2D757AB6-CB0A-41DC-B364-BC287FA9492B","megaEvolStone":"http://www.wikidata.org/entity/Q56676306","megaEvolStoneLabel":"Diancite"},{"pokemon":"http://www.wikidata.org/entity/Q18826862","pokemonLabel":"Hoopa","pokedexNumber":"720","eggGroupStmt":"http://www.wikidata.org/entity/Q26040095","eggGroupStmtLabel":"Undiscovered egg group","type":"http://www.wikidata.org/entity/Q25930811","typeLabel":"dark-type Pokémon","colorLabel":"purple","heightLabel":"50","weightLabel":"9"},{"pokemon":"http://www.wikidata.org/entity/Q18826862","pokemonLabel":"Hoopa","pokedexNumber":"720","eggGroupStmt":"http://www.wikidata.org/entity/Q26040095","eggGroupStmtLabel":"Undiscovered egg group","type":"http://www.wikidata.org/entity/Q25930740","typeLabel":"psychic-type Pokémon","colorLabel":"purple","heightLabel":"50","weightLabel":"9"},{"pokemon":"http://www.wikidata.org/entity/Q18826862","pokemonLabel":"Hoopa","pokedexNumber":"720","eggGroupStmt":"http://www.wikidata.org/entity/Q26040095","eggGroupStmtLabel":"Undiscovered egg group","type":"http://www.wikidata.org/entity/Q25930806","typeLabel":"ghost-type Pokémon","colorLabel":"purple","heightLabel":"50","weightLabel":"9"},{"pokemon":"http://www.wikidata.org/entity/Q17639684","pokemonLabel":"Volcanion","pokedexNumber":"721","eggGroupStmt":"http://www.wikidata.org/entity/Q26040095","eggGroupStmtLabel":"Undiscovered egg group","type":"http://www.wikidata.org/entity/Q25930495","typeLabel":"water-type Pokémon","colorLabel":"red","heightLabel":"170","weightLabel":"195"},{"pokemon":"http://www.wikidata.org/entity/Q17639684","pokemonLabel":"Volcanion","pokedexNumber":"721","eggGroupStmt":"http://www.wikidata.org/entity/Q26040095","eggGroupStmtLabel":"Undiscovered egg group","type":"http://www.wikidata.org/entity/Q25930490","typeLabel":"Q25930490","colorLabel":"red","heightLabel":"170","weightLabel":"195"}]